eutils/__init__.py
eutils/_internal/__init__.py
eutils/_internal/client.py
eutils/_internal/exceptions.py
eutils/_internal/queryservice.py
eutils/_internal/sqlitecache.py
eutils/_internal/utils.py
eutils/_internal/xmlfacades/README.rst
eutils/_internal/xmlfacades/__init__.py
eutils/_internal/xmlfacades/base.py
eutils/_internal/xmlfacades/dbinfo.py
eutils/_internal/xmlfacades/dblist.py
eutils/_internal/xmlfacades/dbsnp.py
eutils/_internal/xmlfacades/einforesult.py
eutils/_internal/xmlfacades/entrezgene.py
eutils/_internal/xmlfacades/entrezgeneset.py
eutils/_internal/xmlfacades/esearchresult.py
eutils/_internal/xmlfacades/gbseq.py
eutils/_internal/xmlfacades/gbset.py
eutils/_internal/xmlfacades/genecommentary.py
eutils/_internal/xmlfacades/medlinecitation.py
eutils/_internal/xmlfacades/pubmedarticle.py
eutils/_internal/xmlfacades/pubmedarticleset.py
eutils/_internal/xmlfacades/pubmedcentralarticle.py
eutils/_internal/xmlfacades/pubmedcentralarticleset.py
eutils/sketchy/__init__.py
eutils/sketchy/clientx.py
eutils-0.6.1.dist-info/licenses/LICENSE.txt
eutils-0.6.1.dist-info/METADATA
eutils-0.6.1.dist-info/WHEEL
eutils-0.6.1.dist-info/top_level.txt
eutils-0.6.1.dist-info/zip-safe
eutils-0.6.1.dist-info/RECORD
