Metadata-Version: 2.4
Name: eutils
Version: 0.6.1
Summary: Python interface to NCBI's eutilities API
Author-email: biocommons contributors <biocommons-dev@googlegroups.com>
License-Expression: Apache-2.0
Project-URL: Documentation, https://biocommons.github.io/eutils/
Project-URL: Homepage, https://github.com/biocommons/eutils/
Project-URL: Issues, https://github.com/biocommons/eutils/issues/
Project-URL: Repository, https://github.com/biocommons/eutils/
Keywords: biocommons,bioinformatics,computational biology,genome variation,genomics,hgvs,variation
Classifier: Development Status :: 5 - Production/Stable
Classifier: Intended Audience :: Developers
Classifier: Programming Language :: Python :: 3
Classifier: Programming Language :: Python :: 3.12
Classifier: Programming Language :: Python :: 3.13
Classifier: Programming Language :: Python :: 3.14
Classifier: Programming Language :: Python
Classifier: Topic :: Scientific/Engineering :: Bio-Informatics
Classifier: Topic :: Scientific/Engineering :: Medical Science Apps.
Classifier: Topic :: Software Development :: Libraries :: Python Modules
Requires-Python: >=3.12
License-File: LICENSE.txt
Requires-Dist: lxml
Requires-Dist: requests
Dynamic: license-file
